colorthief.py
colorthief-0.2.1.dist-info/DESCRIPTION.rst
colorthief-0.2.1.dist-info/METADATA
colorthief-0.2.1.dist-info/metadata.json
colorthief-0.2.1.dist-info/RECORD
colorthief-0.2.1.dist-info/top_level.txt
colorthief-0.2.1.dist-info/WHEEL
